dbversions/DBConfig.py
dbversions/__init__.py
dbversions/config.py
dbversions/db.py
dbversions/gitanalyzer.py
dbversions/data/templates/dbconfig.json
dbversions/data/templates/dbversion-configfile.json
dbversions-0.8.2.data/scripts/dbconfig.py
dbversions-0.8.2.data/scripts/dbversions_init.py
dbversions-0.8.2.data/scripts/dbversions_postcheckout.py
dbversions-0.8.2.dist-info/LICENSE.txt
dbversions-0.8.2.dist-info/METADATA
dbversions-0.8.2.dist-info/RECORD
dbversions-0.8.2.dist-info/WHEEL
dbversions-0.8.2.dist-info/top_level.txt
