Metadata-Version: 2.1
Name: dbversions
Version: 0.8.2
Summary: A python tool and package that helps to keep a corresponding db version for each branch of a git repository.
Home-page: UNKNOWN
Author: Christian Hofbauer
Author-email: chof@gmx.at
License: New BSD License
Platform: UNKNOWN
Requires-Dist: GitPython (>=2.0.8)
